{
	"format_version": "1.8.0",
	"animations": {
		"firing": {
			"animation_length": 1.16,
			"bones": {
				"shotgun": {
					"position": {
						"0.0": {
							"vector": [0, 0, 0]
						},
						"0.12": {
							"vector": [0, 0, 1],
							"easing": "easeInSine"
						},
						"0.24": {
							"vector": [0, 0, 0],
							"easing": "easeInSine"
						}
					}
				},
				"bone": {
					"position": {
						"0.32": {
							"vector": [0, 0, 0]
						},
						"0.52": {
							"vector": [0, 0, 4],
							"easing": "easeInOutSine"
						},
						"0.68": {
							"vector": [0, 0, 0],
							"easing": "easeInOutSine"
						}
					}
				},
				"bone2": {
					"position": {
						"0.0": {
							"vector": [0, 0, -0.5]
						},
						"0.16": {
							"vector": [0, 0, -0.5]
						},
						"0.32": {
							"vector": [0, 0, -0.5]
						}
					},
					"scale": {
						"0.0": {
							"vector": [9, 9, 0]
						},
						"0.28": {
							"vector": [9, 9, 0]
						},
						"0.32": {
							"vector": [0, 0, 0]
						}
					}
				}
			}
		},
		"reload": {
			"animation_length": 0.36,
			"bones": {
				"bone": {
					"position": {
						"0.0": {
							"vector": [0, 0, 0]
						},
						"0.2": {
							"vector": [0, 0, 4],
							"easing": "easeInOutSine"
						},
						"0.36": {
							"vector": [0, 0, 0],
							"easing": "easeInOutSine"
						}
					}
				}
			}
		}
	},
	"geckolib_format_version": 2
}